incept_eval/__init__.py
incept_eval/cli.py
incept_eval/client.py
incept_eval/evaluator.py
incept_eval/submodules/EduBench/LICENSE
incept_eval/submodules/EduBench/README.md
incept_eval/submodules/EduBench/README_zh.md
incept_eval/submodules/EduBench/code/evaluation/evaluation.py
incept_eval/submodules/EduBench/code/generation/AG.py
incept_eval/submodules/EduBench/code/generation/EC.py
incept_eval/submodules/EduBench/code/generation/ES.py
incept_eval/submodules/EduBench/code/generation/IP.py
incept_eval/submodules/EduBench/code/generation/PCC.py
incept_eval/submodules/EduBench/code/generation/PLS.py
incept_eval/submodules/EduBench/code/generation/Q&A.py
incept_eval/submodules/EduBench/code/generation/QG.py
incept_eval/submodules/EduBench/code/generation/TMG.py
incept_eval/submodules/EduBench/code/readme.md
incept_eval/submodules/EduBench/data/all_data/en_data/AG.jsonl
incept_eval/submodules/EduBench/data/all_data/en_data/EC.jsonl
incept_eval/submodules/EduBench/data/all_data/en_data/ES.jsonl
incept_eval/submodules/EduBench/data/all_data/en_data/IP.jsonl
incept_eval/submodules/EduBench/data/all_data/en_data/PCC.jsonl
incept_eval/submodules/EduBench/data/all_data/en_data/PLS.jsonl
incept_eval/submodules/EduBench/data/all_data/en_data/Q&A.jsonl
incept_eval/submodules/EduBench/data/all_data/en_data/QG.jsonl
incept_eval/submodules/EduBench/data/all_data/en_data/TMG.jsonl
incept_eval/submodules/EduBench/data/all_data/model_eval_score/model_sampled_eval_scores.csv
incept_eval/submodules/EduBench/data/all_data/sampled_data/en_data_sampled.jsonl
incept_eval/submodules/EduBench/data/all_data/sampled_data/zh_data_sampled.jsonl
incept_eval/submodules/EduBench/data/all_data/zh_data/AG.jsonl
incept_eval/submodules/EduBench/data/all_data/zh_data/EC.jsonl
incept_eval/submodules/EduBench/data/all_data/zh_data/ES.py
incept_eval/submodules/EduBench/data/all_data/zh_data/IP.jsonl
incept_eval/submodules/EduBench/data/all_data/zh_data/PCC.jsonl
incept_eval-2.1.4.dist-info/METADATA
incept_eval-2.1.4.dist-info/WHEEL
incept_eval-2.1.4.dist-info/entry_points.txt
incept_eval-2.1.4.dist-info/licenses/LICENSE
incept_eval-2.1.4.dist-info/RECORD
