Metadata-Version: 2.4
Name: incept-eval
Version: 2.1.4
Summary: Standalone CLI tool for evaluating educational questions with comprehensive AI-powered assessment
License: MIT
License-File: LICENSE
Keywords: education,evaluation,ai,questions,assessment,edubench,scaffolding
Author: Incept Team
Author-email: noreply@incept.ai
Requires-Python: >=3.11,<3.14
Classifier: Development Status :: 4 - Beta
Classifier: Intended Audience :: Developers
Classifier: Intended Audience :: Education
Classifier: License :: OSI Approved :: MIT License
Classifier: Programming Language :: Python :: 3
Classifier: Programming Language :: Python :: 3.11
Classifier: Programming Language :: Python :: 3.12
Classifier: Programming Language :: Python :: 3.13
Classifier: Topic :: Education
Requires-Dist: anthropic (>=0.70.0)
Requires-Dist: click (>=8.1.7,<9.0.0)
Requires-Dist: openai (>=1.100.2)
Requires-Dist: pandas (>=2.0.0)
Requires-Dist: pydantic (>=2.0.0)
Requires-Dist: python-dotenv (>=1.0.0)
Requires-Dist: requests (>=2.31.0,<3.0.0)
Requires-Dist: tiktoken (>=0.11.0)
Requires-Dist: torch (>=2.8.0)
Requires-Dist: tqdm (>=4.66.0)
Requires-Dist: transformers (>=4.55.3)
Project-URL: Homepage, https://github.com/incept-ai/incept-eval
Project-URL: Repository, https://github.com/incept-ai/incept-eval
